<?xml version="1.0" encoding="UTF-8" standalone="yes"?>
<contentHaul xmlns:a="http://www.appian.com/ae/types/2009">
    <rule>
        <name>PERM_integrationCheckAssuranceLodgementDate</name>
        <uuid>_a-0000da39-53c8-8000-9ba2-011c48011c48_8025</uuid>
        <description>check if the assurance lodgmement date is future otherwise returns false</description>
        <parentUuid>_a-0000da88-6c19-8000-9ba2-011c48011c48_11453</parentUuid>
        <visibility>
            <advertise>false</advertise>
            <hierarchy>true</hierarchy>
            <indexable>true</indexable>
            <quota>false</quota>
            <searchable>true</searchable>
            <system>false</system>
            <unlogged>false</unlogged>
        </visibility>
        <definition>= if(
  ri!assuranceLodgementDate_dt &gt; now(),
  #&quot;_a-0000da39-53c8-8000-9ba2-011c48011c48_7111&quot;(
    #&quot;_a-0000da39-53c8-8000-9ba2-011c48011c48_7108&quot;(
      818,
      838,
      &quot;9&quot;,
      819
    ),
    ri!field_txt,
    ri!assuranceLodgementDate_dt
  ),
  {}
)</definition>
        <namedTypedValue>
            <name>assuranceLodgementDate_dt</name>
            <type>
                <name>dateTime</name>
                <namespace>http://www.w3.org/2001/XMLSchema</namespace>
            </type>
        </namedTypedValue>
        <namedTypedValue>
            <name>field_txt</name>
            <type>
                <name>string</name>
                <namespace>http://www.w3.org/2001/XMLSchema</namespace>
            </type>
            <value/>
        </namedTypedValue>
        <preferredEditor>legacy</preferredEditor>
        <offlineEnabled>false</offlineEnabled>
    </rule>
    <roleMap public="true">
        <role allowForAll="false" inherit="true" name="readers">
            <users/>
            <groups/>
        </role>
        <role allowForAll="false" inherit="true" name="authors">
            <users/>
            <groups/>
        </role>
        <role allowForAll="false" inherit="true" name="administrators">
            <users/>
            <groups/>
        </role>
        <role allowForAll="false" inherit="false" name="denyReaders">
            <users/>
            <groups/>
        </role>
        <role allowForAll="false" inherit="false" name="denyAuthors">
            <users/>
            <groups/>
        </role>
        <role allowForAll="false" inherit="false" name="denyAdministrators">
            <users/>
            <groups/>
        </role>
    </roleMap>
</contentHaul>
