<?xml version="1.0" encoding="UTF-8" standalone="yes"?>
<contentHaul xmlns:a="http://www.appian.com/ae/types/2009">
    <rule>
        <name>CEVL_getCaRERelatedQuestionsToUpdateMap_VWByJustificationAnswerId</name>
        <uuid>_a-0000dba1-dfd2-8000-9ba2-011c48011c48_20703</uuid>
        <description>This rule retrieves related questions for the given Justification Answer Ids</description>
        <parentUuid>_a-0000d9e6-bfac-8000-9ba2-011c48011c48_1521</parentUuid>
        <visibility>
            <advertise>false</advertise>
            <hierarchy>true</hierarchy>
            <indexable>true</indexable>
            <quota>false</quota>
            <searchable>true</searchable>
            <system>false</system>
            <unlogged>false</unlogged>
        </visibility>
        <definition>if(#&quot;_a-0000db6c-d5e0-8000-9ba2-011c48011c48_12573&quot;(ri!justificationAnswerIds),
  {},
  #&quot;_a-0000dba1-dfd2-8000-9ba2-011c48011c48_20691&quot;(ri!justificationAnswerIds)
)</definition>
        <namedTypedValue>
            <name>justificationAnswerIds</name>
            <type>
                <name>Integer?list</name>
                <namespace>http://www.appian.com/ae/types/2009</namespace>
            </type>
        </namedTypedValue>
        <preferredEditor>legacy</preferredEditor>
        <offlineEnabled>false</offlineEnabled>
    </rule>
    <roleMap public="true">
        <role allowForAll="false" inherit="true" name="readers">
            <users/>
            <groups/>
        </role>
        <role allowForAll="false" inherit="true" name="authors">
            <users/>
            <groups/>
        </role>
        <role allowForAll="false" inherit="true" name="administrators">
            <users/>
            <groups/>
        </role>
        <role allowForAll="false" inherit="false" name="denyReaders">
            <users/>
            <groups/>
        </role>
        <role allowForAll="false" inherit="false" name="denyAuthors">
            <users/>
            <groups/>
        </role>
        <role allowForAll="false" inherit="false" name="denyAdministrators">
            <users/>
            <groups/>
        </role>
    </roleMap>
    <typedValue>
        <type>
            <name>RuleTestConfig</name>
            <namespace>http://www.appian.com/ae/types/2009</namespace>
        </type>
        <value>
            <a:ruleInputTestConfigs>
                <a:value xmlns:xsd="http://www.w3.org/2001/XMLSchema" xmlns:xsi="http://www.w3.org/2001/XMLSchema-instance" xsi:type="xsd:string"/>
                <a:nameRef>justificationAnswerIds</a:nameRef>
            </a:ruleInputTestConfigs>
        </value>
    </typedValue>
</contentHaul>
