<?xml version="1.0" encoding="UTF-8" standalone="yes"?>
<contentHaul xmlns:a="http://www.appian.com/ae/types/2009">
    <queryRule>
        <name>CT_getPermitActivityStandardTextMapDetailsByPermitActivityId</name>
        <uuid>bb9ad989-9367-43f5-b01b-8e6455efc19c</uuid>
        <description>This query rule fetches all permit activity standard text map details based on permit activity id</description>
        <folderUuid>_a-0000da88-6c19-8000-9ba2-011c48011c48_11471</folderUuid>
        <dataStoreEntityCompositeUuid>f867bf43-ae2e-4ea2-be8a-344e4e725d4d@_a-0000d9e6-bfac-8000-9ba2-011c48011c48_1299</dataStoreEntityCompositeUuid>
        <params>
            <param>
                <description></description>
                <name>permitActivityId</name>
                <type>{http://www.appian.com/ae/types/2009}Integer?list</type>
            </param>
            <param>
                <description></description>
                <name>active</name>
                <type>{http://www.w3.org/2001/XMLSchema}int</type>
            </param>
        </params>
        <filters>
            <filter>
                <field>
                    <name>permitActivityId</name>
                    <type>{http://www.w3.org/2001/XMLSchema}int</type>
                </field>
                <op>in</op>
                <value>permitActivityId</value>
                <valueType>PARAMETER</valueType>
            </filter>
            <filter>
                <field>
                    <name>active</name>
                    <type>{http://www.w3.org/2001/XMLSchema}int</type>
                </field>
                <op>=</op>
                <value>active</value>
                <valueType>PARAMETER</valueType>
            </filter>
        </filters>
        <orderings/>
    </queryRule>
    <roleMap public="false">
        <role allowForAll="false" inherit="true" name="readers">
            <users/>
            <groups/>
        </role>
        <role allowForAll="false" inherit="true" name="authors">
            <users/>
            <groups/>
        </role>
        <role allowForAll="false" inherit="true" name="administrators">
            <users/>
            <groups/>
        </role>
        <role allowForAll="false" inherit="false" name="denyReaders">
            <users/>
            <groups/>
        </role>
        <role allowForAll="false" inherit="false" name="denyAuthors">
            <users/>
            <groups/>
        </role>
        <role allowForAll="false" inherit="false" name="denyAdministrators">
            <users/>
            <groups/>
        </role>
    </roleMap>
</contentHaul>
