<?xml version="1.0" encoding="UTF-8" standalone="yes"?>
<contentHaul xmlns:a="http://www.appian.com/ae/types/2009">
    <queryRule>
        <name>CT_getCaREEvaluationCampaignDetailsByCaREEvaluationCampaignId</name>
        <uuid>d12a0db0-fbd0-493d-a547-26dac4d37308</uuid>
        <description>This query rule fetches all CaRE evaluation campaign details by CaRE evaluation  campaign id</description>
        <folderUuid>_a-0000d9e6-bfac-8000-9ba2-011c48011c48_1233</folderUuid>
        <dataStoreEntityCompositeUuid>ac9b6f19-d77d-4190-b90a-11b4bd562ea7@_a-0000d9e6-bfac-8000-9ba2-011c48011c48_1299</dataStoreEntityCompositeUuid>
        <params>
            <param>
                <description></description>
                <name>careEvaluationCampaignId</name>
                <type>{http://www.w3.org/2001/XMLSchema}int</type>
            </param>
        </params>
        <filters>
            <filter>
                <field>
                    <name>careEvaluationCampaignId</name>
                    <type>{http://www.w3.org/2001/XMLSchema}int</type>
                </field>
                <op>=</op>
                <value>careEvaluationCampaignId</value>
                <valueType>PARAMETER</valueType>
            </filter>
        </filters>
        <orderings/>
    </queryRule>
    <roleMap public="false">
        <role allowForAll="false" inherit="true" name="readers">
            <users/>
            <groups/>
        </role>
        <role allowForAll="false" inherit="true" name="authors">
            <users/>
            <groups/>
        </role>
        <role allowForAll="false" inherit="true" name="administrators">
            <users/>
            <groups/>
        </role>
        <role allowForAll="false" inherit="false" name="denyReaders">
            <users/>
            <groups/>
        </role>
        <role allowForAll="false" inherit="false" name="denyAuthors">
            <users/>
            <groups/>
        </role>
        <role allowForAll="false" inherit="false" name="denyAdministrators">
            <users/>
            <groups/>
        </role>
    </roleMap>
</contentHaul>
